VBasicCalculator/__init__.py
VBasicCalculator-0.1.dist-info/LICENCE.txt
VBasicCalculator-0.1.dist-info/METADATA
VBasicCalculator-0.1.dist-info/WHEEL
VBasicCalculator-0.1.dist-info/top_level.txt
VBasicCalculator-0.1.dist-info/RECORD
