Metadata-Version: 2.1
Name: VBasicCalculator
Version: 0.1
Summary: BASIC CALCULATOR
Home-page: UNKNOWN
Author: VENMUHIL BHARATHI G
Author-email: venmuhilvmb@gmail.com
License: UNKNOWN
Platform: UNKNOWN
Classifier: Programming Language :: Python :: 3
Classifier: License :: OSI Approved :: MIT License
Classifier: Operating System :: OS Independent
